single_cycle_cpu/datapath/npc.v
module npc(PC, NPC, NPCop, target, ext_result, zero);
    input [31:0] PC;
    input [25: 0] target;
    input [31 :0] ext_result;
    input [3: 0] NPCop;
    input zero;

    output reg[31: 0] NPC;


    // 所有的跳转信号，虽然写的时候只支持两种Jump和Branch
    parameter JUMP = 4'b0000;
    parameter JAL  = 4'b0001;
    parameter BEQ  = 4'b0010;
    parameter BNE  = 4'b0011;
    parameter BGEZ = 4'b0100;
    parameter BGTZ = 4'b0101;
    parameter BLEZ = 4'b0110;
    parameter BLTZ = 4'b0111;
    parameter JR   = 4'b1000;
    parameter JALR = 4'b1000;
    parameter ADD4 = 4'b1111;  // 正常的 pc + 4 的情况

  always @(*) begin
    case(NPCop)
        JUMP : NPC = {PC[31: 28], target << 2};
        BEQ : NPC = (zero == 1) ? (PC + 4 + (ext_result << 2)): (PC + 4);
        ADD4: NPC = PC + 4;
    endcase
    // $display("(NPC.v) zero = %h npc = %h", zero, NPC);
  end

endmodule

pipline_cpu_1/datapath/dm.v
module dm_4k(addr, din, we, clk, dout);
    input [31: 0] addr;  // 要读写的数据的地址
    input [31: 0] din; // 要写入数据
    input we; // 写使能信号
    input clk;

    output [31: 0] dout; //读出数据

    reg [31: 0] dm[1023: 0]; // 数据寄存器

    initial
      $readmemh("data.txt", dm, 0 ,1023);

  always @(posedge clk) begin 
    if(we)   // 写入数据
      begin
        dm[addr] = din;
        $display("dm:%d<=%h", addr, din);
      end
    end

  assign dout = dm[addr];   // 读出数据

endmodule

single_cycle_cpu/datapath/regfile.v
module regfile(rs, rt, rd, rs_data, rt_data, wd, wr, RegDst, clk);
    input [4: 0] rs, rt, rd; // 三个寄存器编号信号
    input[31: 0] wd; // 写入寄存器的值
    input wr; // 决定能否写入寄存器的信号
    input clk; // 时钟信号
    input RegDst; //1:代表写入rt， 0：代表写入rd

    output [31: 0] rs_data, rt_data; // 两个寄存器读出的值

    reg[4: 0] addr;
    reg [31: 0] rf[31: 0];  // 31个32位寄存器

    integer i;
    initial begin
      for (i = 0; i < 32; i = i + 1)
        rf[i] = 0;
    end

  always @(posedge clk) begin
    if (wr)begin 
          addr = (RegDst == 1) ? rt : rd;
          rf[addr] = wd;  // 写入Rd
          // $display("(regfile.v) WRITE MODE rt: %d, rd: %d", rt, rd);
          $display("reg:$%d<=%h",addr, wd);
        end
  end

  assign rs_data = (rs == 0) ? 32'b0: rf[rs];  // 读出数据
  assign rt_data = (rt == 0) ? 32'b0: rf[rt];
  

endmodule

single_cycle_cpu/datapath/mux.v
// 判断ALU的第二个输入是来自立即数还是寄存器
module mux1(Rt_data, Ext_result, Data, ALUSrc);
    input [31:0] Rt_data;        // 寄存器的第二个输出
    input [31:0] Ext_result;     // 符号扩展后的值
    input ALUSrc;      // 0：选择寄存器的第二个输出 1：立即数扩展后的值
    output reg [31:0] Data;     // 选择后的值

    always @(*)
    begin
        if (ALUSrc)
            begin
                Data = Ext_result;
                // $display("(MUX.v) select ext_result: %h", Data);
            end
        else  
            begin
                Data = Rt_data;
                // $display("(MUX.v) select Rt_data: %h", Data);
            end       
    end
endmodule

// 控制写入regfile的数据来自ALU还是数据存储器
module mux2(ALUoutput, MEMouput, Data, MemtoReg);
    input [31:0] ALUoutput;        // ALU的输出
    input [31:0] MEMouput;     // 数据存储器的输出
    input MemtoReg;      // 0：选择ALU的输出 1：选择数据存储器的输出
    output reg [31:0] Data;     // 选择后的值

    always @(*)
    begin
        if (MemtoReg)
            begin
                Data = MEMouput;
                // $display("(MUX.v) select ALU_output: %h", Data);
            end
        else  
            begin
                Data = ALUoutput;
                // $display("(MUX.v) select DATAMEM_output: %h", Data);
            end       
    end
endmodule

single_cycle_cpu/datapath/alu.v
module alu (a, b, zero, result, alu_ctrl, shamt);
    input [31:0] a,b;  // 两个操作数
    input [3: 0] alu_ctrl;
    input [4: 0] shamt;
    output zero;  // 运算的结果是否为0的信号
    output reg[31:0] result; // 输出运算结果

   // 支持的所有ALU运算
    parameter AND   = 4'b0000;
    parameter OR    = 4'b0001;
    parameter ADD   = 4'b0010;
    parameter XOR   = 4'b0011;
    parameter ORI   = 4'b0100;
    parameter ADDIU = 4'b0101;
    parameter SUB   = 4'b0110;
    parameter ADDI  = 4'b0111;
    parameter SLL   = 4'b1000;
    parameter SLT   = 4'b0111;
    parameter LUI   = 4'b1111;  // 16位扩展
    
    always@(*)
    begin
        case(alu_ctrl)
            ADD : result = a + b;
            SUB : result = a - b;
            AND : result = a & b;
            OR  : result = a | b;
            SLT : result = (a < b);
            XOR : result = a ^ b;
            LUI : result = (b << 16);  // 对于LUI指令，左移16位
            ADDIU : result = a + b;
            ORI : result = a | b;
            SLL : result = (a << shamt);
        endcase
        // $display("(ALU.v) alu_ctrl: %b ,a: %h, b: %h, result: %h ", alu_ctrl, a, b, result);
    end

    assign zero = (result == 0);

endmodule

single_cycle_cpu/datapath/ext.v
module ext(imm, ext_result, ext_op);    // 符号扩展的模块
  input [15: 0] imm;       //需要符号扩展的16位立即数
  output reg [31: 0] ext_result;      // 32位扩展结果
  input ext_op;    // 控制是否进行有符号扩展的信号

  always @(*) begin
    if(ext_op == 1)
        ext_result = {{16{imm[15]}}, imm[15: 0]};
    else
        ext_result = {{16{1'b0}}, imm[15: 0]};
    
    // $display("(ext.v) imm: %h, ext_result: %h", imm, ext_result);
  end
endmodule

pipline_cpu_1/datapath/im.v
module im_4k(pc, dout);
    input [31: 0] pc; // 地址信号
    output reg [31:0] dout; // 要输出的指令

    reg [31:0] im[1023: 0]; //4k个字宽为32位的寄存器

    initial
        $readmemh("code.txt", im, 0, 1023);

    always @(*) begin
        dout = im[pc[11: 2]];  // 由于只支持4k存储，所以使用12位就行
        // $display("(IM.v) pc: %h", pc);
        // $display("(IM.v) instruction: %h", dout);
    end
     
endmodule

datapath/pc.v
module pc(npc, pc, rst, clk);

  input clk, rst; // 时钟信号，复位信号
  input [31: 0] npc; // 32位输入，指令的地址
  output reg [31: 0] pc;  // 32位输出，指令的地址

  initial
    begin
        pc = 32'h3000;
    end

  always @(posedge clk or posedge rst) begin
    if (rst)
        begin
          pc = 32'h3000; // 复位信号，将DO设置为0
          // $display("(PC.v) pc: %h", pc);
        end
    else
        pc = npc;
  end

endmodule

datapath/datapath.v
`include "./datapath/pc.v"
`include "./datapath/im.v"
`include "./datapath/regfile.v"
`include "./datapath/alu.v"
`include "./datapath/dm.v"
`include "./datapath/ext.v"
`include "./datapath/npc.v"
`include "./datapath/mux.v"

module datapath(clk, rst, op, func, RegDst, ALUSrc, MemtoReg, RegWr, MemWr, NPCop, ExtOp, ALUctr);
    // op,  // 指令的op段
    // func,  // 指令的func段
    // RegWr,   //寄存器能否写入的信号
    // ALUSrc,   // ALU是否有输入来自立即数
    // RegDst,    // 控制寄存器写入地址
    // MemtoReg,  // 数据存储器能否写入寄存器
    // MemWr,   // 数据存储器能否被写入
    // Branch,    // 是否是分支指令
    // Jump,    // 是否是无条件跳转指令
    // ExtOp,    // 是否符号扩展
    // ALUctr    // 控制ALU功能
    input clk, rst, RegDst, ALUSrc, MemtoReg, RegWr, MemWr, ExtOp;
    input[3:0] ALUctr, NPCop;

    output[5:0] op, func;


    wire [31: 0] instruction;
    wire [31:0] PC, NPC;

    assign op = instruction[31: 26];
    assign func = instruction[5: 0];

    wire[4:0]  Rs = instruction[25: 21];
    wire[4: 0] Rt = instruction[20: 16];
    wire[4: 0] Rd = instruction[15: 11];
    wire[31: 0] rs_data, rt_data;

    wire Zero;
    wire [4: 0] shamt = instruction[10: 6];
    wire [31: 0] data, ext_result, result;
    wire [15: 0] imm16 = instruction[15: 0];

    wire [31: 0] dout, wd;
    wire [25: 0] target = instruction[25: 0];

    pc pc(NPC, PC, rst, clk);

    im_4k im(PC, instruction);

    ext SignExt(imm16, ext_result, ExtOp);

    mux1 aluMux(rt_data, ext_result, data, ALUSrc);

    alu alu(rs_data, data, zero, result, ALUctr, shamt);

    mux2 regMux(result, dout, wd, MemtoReg);

    regfile regfile(Rs, Rt, Rd, rs_data, rt_data, wd, RegWr, RegDst, clk);

    dm_4k dm(result, rt_data, MemWr, clk, dout);  //这里的result是地址

    npc npc(PC, NPC, NPCop, target, ext_result, zero);
endmodule

control/controller.v
module controller(op, func, RegDst, ALUSrc, MemtoReg, RegWr, MemWr, NPCop, ExtOp, ALUctr);
    // op,  // 指令的op段
    // func,  // 指令的func段
    // RegDst,    // 寄存器写入地址
    // ALUSrc,   // ALU是否接受立即数
    // MemtoReg,  // 数据存储器能否写入寄存器
    // RegWr,   //寄存器能否写入的信号
    // MemWr,   // 数据存储器能否被写入
    // NPCop, // 判断跳转类型是Jump，Beq还是其他
    // ExtOp,    // 是否符号扩展
    // ALUctr    // 控制ALU功能

    input [5:0]	op, func;
	
	output reg RegDst, ALUSrc, MemtoReg, RegWr, MemWr, ExtOp;
	output reg[3:0]	ALUctr, NPCop;

    // 所有的跳转信号，虽然写的时候只支持两种Jump和Branch
    parameter JUMP = 4'b0000;
    parameter JAL  = 4'b0001;
    parameter BEQ  = 4'b0010;
    parameter BNE  = 4'b0011;
    parameter BGEZ = 4'b0100;
    parameter BGTZ = 4'b0101;
    parameter BLEZ = 4'b0110;
    parameter BLTZ = 4'b0111;
    parameter JR   = 4'b1000;
    parameter JALR = 4'b1000;
    parameter ADD4 = 4'b1111;  // 正常的 pc + 4 的情况

    // 支持的所有ALU运算
    parameter AND   = 4'b0000;
    parameter OR    = 4'b0001;
    parameter ADD   = 4'b0010;
    parameter XOR   = 4'b0011;
    parameter ORI   = 4'b0100;
    parameter ADDIU = 4'b0101;
    parameter SUB   = 4'b0110;
    parameter ADDI  = 4'b0111;
    parameter SLL   = 4'b1000;
    parameter SLT   = 4'b0111;   
    parameter LUI   = 4'b1111;  // 实在没办法处理这个，特殊处理吧

    always @(*) begin
        case(op)
            6'b000000: //  R型指令 
                begin
                    RegDst   = 1'b0;
                    ALUSrc   = 1'b0;
                    MemtoReg = 1'b0; 
                    RegWr    = 1'b1; // 可以写到寄存器
                    MemWr    = 1'b0; // 不需要写存储器
                    NPCop    = ADD4;
                    case(func)
                            6'b100000: ALUctr = ADD;
                            6'b100010: ALUctr = SUB;
                            6'b100100: ALUctr = AND;
                            6'b100101: ALUctr = OR;
                            6'b101010: ALUctr = SLT;
                            6'b100110: ALUctr = XOR;
                            6'b000000: ALUctr = SLL;
                    endcase
                end
            
            6'b001001:	//addiu
                begin
                    RegDst   = 1'b1;
                    ALUSrc   = 1'b1;
                    MemtoReg = 1'b0; 
                    RegWr    = 1'b1; // 可以写到寄存器
                    MemWr    = 1'b0; // 不需要写存储器
                    NPCop    = ADD4;
                    ExtOp    = 1'b0;
                    ALUctr	 = ADDIU;				//addiu
                end

            6'b001000:	//addi
                begin
                    RegDst   = 1'b1;
                    ALUSrc   = 1'b1;
                    MemtoReg = 1'b0; 
                    RegWr    = 1'b1; // 可以写到寄存器
                    MemWr    = 1'b0; // 不需要写存储器
                    NPCop    = ADD4;
                    ExtOp    = 1'b1;
                    ALUctr	 = ADDIU;				//addi
                end

            6'b001101:	//ori
                begin
                    RegDst   = 1'b1;
                    ALUSrc   = 1'b1;
                    MemtoReg = 1'b0; 
                    RegWr    = 1'b1; // 可以写到寄存器
                    MemWr    = 1'b0; // 不需要写存储器
                    NPCop    = ADD4;
                    ExtOp    = 1'b1;
                    ALUctr	=	ORI;				//ori
                end
            
            6'b001111:	//lui
                begin
                    RegDst   = 1'b1;  // rt作为reg的写入地址
                    ALUSrc   = 1'b1;
                    MemtoReg = 1'b0;  // 用于控制数据存储器能否输出数据到寄存器
                    RegWr    = 1'b1; // 写寄存器
                    MemWr    = 1'b0; // 用于控制数据存储器可否被写入
                    ExtOp    = 1'b1;
                    ALUctr   = LUI ;
                    NPCop    = ADD4;			//lui
                end

            6'b100011:	//lw
                begin
                    RegDst   = 1'b1;
                    MemtoReg = 1'b1; 
                    RegWr    = 1'b1; // 可以写到寄存器
                    MemWr    = 1'b0; // 不需要写存储器
                    NPCop    = ADD4;
                    ExtOp    = 1'b1;
                    ALUSrc   = 1'b1;
                    ALUctr   = ADD;
                    NPCop   =  ADD4;		//addu
                end

            6'b101011:	//sw
                begin
                    RegDst   = 1'b1;
                    MemtoReg = 1'b0; 
                    RegWr    = 1'b0; // 读寄存器
                    MemWr    = 1'b1; // 不需要写存储器
                    NPCop    = ADD4;
                    ExtOp    = 1'b1;
                    ALUSrc   = 1'b1;
                    ALUctr   = ADD;
                    NPCop   =   ADD4;			//addu
                end

            6'b000100:	//beq
                begin
                    RegDst   = 1'b0;
                    MemtoReg = 1'b0; 
                    RegWr    = 1'b0; // 读寄存器
                    MemWr    = 1'b0; // 不需要写存储器
                    NPCop    = BEQ;
                    ALUSrc   = 1'b0;
                    ALUctr   = SUB;
                    NPCop    = BEQ;			//subu
                end

            6'b000010:	//jump
                begin
                    RegDst   = 1'b1;
                    MemtoReg = 1'b0; 
                    RegWr    = 1'b0;
                    MemWr    = 1'b0; // 不需要写存储器
                    NPCop   = JUMP;			//Jump
                end
        endcase

        // $display("(controller.v) op: %b func: %b", op, func);
        // $display("(controller.v) RegDst: %b, ALUSrc: %b, MemtoReg: %b, RegWr: %b, MemWr: %b, ExtOp: %b", RegDst, ALUSrc, MemtoReg, RegWr, MemWr, ExtOp);
        // $display("(controller.v) ALUctr: %b, NPCop: %b", ALUctr, NPCop);
    end


endmodule

mips.v
`include "./control/controller.v"
`include "./datapath/datapath.v"

module Mips(clk, rst);
    input clk;
    input rst;

    // signal
    wire [5 : 0] op;
    wire [5: 0] func;
    wire RegDst;
    wire ALUSrc;
    wire MemtoReg;
    wire RegWr;
    wire MemWr;
    wire [3: 0] NPCop;
    wire ExtOp;
    wire [3: 0] ALUctr;


    // 根据传入的op，func，rt，生成各种信号并输出
    controller controller(
        op,  // 指令的op段
        func,  // 指令的func段
        RegDst,    // 寄存器写入地址
        ALUSrc,   // ALU是否接受立即数
        MemtoReg,  // 数据存储器能否写入寄存器
        RegWr,   //寄存器能否写入的信号
        MemWr,   // 数据存储器能否被写入
        NPCop, // 判断跳转类型是Jump，Beq还是其他
        ExtOp,    // 是否符号扩展
        ALUctr    // 控制ALU功能
        );
        
    datapath datapath(
        clk,
        rst,
        op,       //指令的op段
        func,     // 指令的func段
        RegDst,    // 控制寄存器写入地址
        ALUSrc,   // ALU是否接受立即数 
        MemtoReg,   // 数据存储器能否写入寄存器
        RegWr,     // 寄存器能否写入的信号
        MemWr,     // 数据存储器能否写入的信号
        NPCop, // 判断跳转类型是Jump，Beq还是其他
        ExtOp,    // 是否符号扩展的信号
        ALUctr    // 控制ALU功能的信号
        );

    
endmodule

single_cycle_cpu/testBench.v
`timescale 1ps/1ps
`include "./mips.v"

module Testbench();
    reg    clk ;
    reg    rst ;
    
    Mips mips(clk, rst);

    initial 
        begin
            $dumpfile("testBench.vcd");
            $dumpvars;
            clk <= 0 ;
            rst <= 1 ;
            #10 rst <= 0 ; 
            #2000 $finish;
        end
            
    integer cnt = 0;
    
    always@(*)
    begin
         #20 clk<=~clk;
         cnt = cnt + 1;
    end
       
    
endmodule

single_cycle_cpu/testBench.vcd
$date
	Fri Dec 02 16:48:11 2022
$end
$version
	Icarus Verilog
$end
$timescale
	1ps
$end
$scope module Testbench $end
$var reg 1 ! clk $end
$var reg 1 " rst $end
$var integer 32 # cnt [31:0] $end
$scope module mips $end
$var wire 1 ! clk $end
$var wire 1 " rst $end
$var wire 6 $ op [5:0] $end
$var wire 6 % func [5:0] $end
$var wire 1 & RegWr $end
$var wire 1 ' RegDst $end
$var wire 4 ( NPCop [3:0] $end
$var wire 1 ) MemtoReg $end
$var wire 1 * MemWr $end
$var wire 1 + ExtOp $end
$var wire 4 , ALUctr [3:0] $end
$var wire 1 - ALUSrc $end
$scope module controller $end
$var wire 6 . op [5:0] $end
$var wire 6 / func [5:0] $end
$var parameter 4 0 ADD $end
$var parameter 4 1 ADD4 $end
$var parameter 4 2 ADDI $end
$var parameter 4 3 ADDIU $end
$var parameter 4 4 AND $end
$var parameter 4 5 BEQ $end
$var parameter 4 6 BGEZ $end
$var parameter 4 7 BGTZ $end
$var parameter 4 8 BLEZ $end
$var parameter 4 9 BLTZ $end
$var parameter 4 : BNE $end
$var parameter 4 ; JAL $end
$var parameter 4 < JALR $end
$var parameter 4 = JR $end
$var parameter 4 > JUMP $end
$var parameter 4 ? LUI $end
$var parameter 4 @ OR $end
$var parameter 4 A ORI $end
$var parameter 4 B SLL $end
$var parameter 4 C SLT $end
$var parameter 4 D SUB $end
$var parameter 4 E XOR $end
$var reg 1 - ALUSrc $end
$var reg 4 F ALUctr [3:0] $end
$var reg 1 + ExtOp $end
$var reg 1 * MemWr $end
$var reg 1 ) MemtoReg $end
$var reg 4 G NPCop [3:0] $end
$var reg 1 ' RegDst $end
$var reg 1 & RegWr $end
$upscope $end
$scope module datapath $end
$var wire 1 - ALUSrc $end
$var wire 4 H ALUctr [3:0] $end
$var wire 1 + ExtOp $end
$var wire 1 * MemWr $end
$var wire 1 ) MemtoReg $end
$var wire 4 I NPCop [3:0] $end
$var wire 1 ' RegDst $end
$var wire 1 & RegWr $end
$var wire 1 ! clk $end
$var wire 1 " rst $end
$var wire 1 J zero $end
$var wire 32 K wd [31:0] $end
$var wire 26 L target [25:0] $end
$var wire 5 M shamt [4:0] $end
$var wire 32 N rt_data [31:0] $end
$var wire 32 O rs_data [31:0] $end
$var wire 32 P result [31:0] $end
$var wire 6 Q op [5:0] $end
$var wire 32 R instruction [31:0] $end
$var wire 16 S imm16 [15:0] $end
$var wire 6 T func [5:0] $end
$var wire 32 U ext_result [31:0] $end
$var wire 32 V dout [31:0] $end
$var wire 32 W data [31:0] $end
$var wire 5 X Rt [4:0] $end
$var wire 5 Y Rs [4:0] $end
$var wire 5 Z Rd [4:0] $end
$var wire 32 [ PC [31:0] $end
$var wire 32 \ NPC [31:0] $end
$scope module SignExt $end
$var wire 1 + ext_op $end
$var wire 16 ] imm [15:0] $end
$var reg 32 ^ ext_result [31:0] $end
$upscope $end
$scope module alu $end
$var wire 4 _ alu_ctrl [3:0] $end
$var wire 5 ` shamt [4:0] $end
$var wire 1 J zero $end
$var wire 32 a b [31:0] $end
$var wire 32 b a [31:0] $end
$var parameter 4 c ADD $end
$var parameter 4 d ADDI $end
$var parameter 4 e ADDIU $end
$var parameter 4 f AND $end
$var parameter 4 g LUI $end
$var parameter 4 h OR $end
$var parameter 4 i ORI $end
$var parameter 4 j SLL $end
$var parameter 4 k SLT $end
$var parameter 4 l SUB $end
$var parameter 4 m XOR $end
$var reg 32 n result [31:0] $end
$upscope $end
$scope module aluMux $end
$var wire 1 - ALUSrc $end
$var wire 32 o Ext_result [31:0] $end
$var wire 32 p Rt_data [31:0] $end
$var reg 32 q Data [31:0] $end
$upscope $end
$scope module dm $end
$var wire 32 r addr [31:0] $end
$var wire 1 ! clk $end
$var wire 32 s dout [31:0] $end
$var wire 1 * we $end
$var wire 32 t din [31:0] $end
$upscope $end
$scope module im $end
$var wire 32 u pc [31:0] $end
$var reg 32 v dout [31:0] $end
$upscope $end
$scope module npc $end
$var wire 4 w NPCop [3:0] $end
$var wire 32 x ext_result [31:0] $end
$var wire 26 y target [25:0] $end
$var wire 1 J zero $end
$var wire 32 z PC [31:0] $end
$var parameter 4 { ADD4 $end
$var parameter 4 | BEQ $end
$var parameter 4 } BGEZ $end
$var parameter 4 ~ BGTZ $end
$var parameter 4 !" BLEZ $end
$var parameter 4 "" BLTZ $end
$var parameter 4 #" BNE $end
$var parameter 4 $" JAL $end
$var parameter 4 %" JALR $end
$var parameter 4 &" JR $end
$var parameter 4 '" JUMP $end
$var reg 32 (" NPC [31:0] $end
$upscope $end
$scope module pc $end
$var wire 1 ! clk $end
$var wire 32 )" npc [31:0] $end
$var wire 1 " rst $end
$var reg 32 *" pc [31:0] $end
$upscope $end
$scope module regMux $end
$var wire 32 +" ALUoutput [31:0] $end
$var wire 32 ," MEMouput [31:0] $end
$var wire 1 ) MemtoReg $end
$var reg 32 -" Data [31:0] $end
$upscope $end
$scope module regfile $end
$var wire 1 ' RegDst $end
$var wire 1 ! clk $end
$var wire 5 ." rd [4:0] $end
$var wire 5 /" rs [4:0] $end
$var wire 5 0" rt [4:0] $end
$var wire 32 1" wd [31:0] $end
$var wire 1 & wr $end
$var wire 32 2" rt_data [31:0] $end
$var wire 32 3" rs_data [31:0] $end
$var reg 5 4" addr [4:0] $end
$var integer 32 5" i [31:0] $end
$upscope $end
$upscope $end
$upscope $end
$upscope $end
$enddefinitions $end
$comment Show the parameter values. $end
$dumpall
b0 '"
b1000 &"
b1000 %"
b1 $"
b11 #"
b111 ""
b110 !"
b101 ~
b100 }
b10 |
b1111 {
b11 m
b110 l
b111 k
b1000 j
b100 i
b1 h
b1111 g
b0 f
b101 e
b111 d
b10 c
b11 E
b110 D
b111 C
b1000 B
b100 A
b1 @
b1111 ?
b0 >
b1000 =
b1000 <
b1 ;
b11 :
b111 9
b110 8
b101 7
b100 6
b10 5
b0 4
b101 3
b111 2
b1111 1
b10 0
$end
#0
$dumpvars
b100000 5"
bx 4"
b0 3"
b0 2"
b10 1"
b10001 0"
b0 /"
b0 ."
b10 -"
b1 ,"
b10 +"
b11000000000000 *"
b11000000000100 )"
b11000000000100 ("
b11000000000000 z
b100010000000000000010 y
b10 x
b1111 w
b100100000100010000000000000010 v
b11000000000000 u
b0 t
b1 s
b10 r
b10 q
b0 p
b10 o
b10 n
b0 b
b10 a
b0 `
b101 _
b10 ^
b10 ]
b11000000000100 \
b11000000000000 [
b0 Z
b0 Y
b10001 X
b10 W
b1 V
b10 U
b10 T
b10 S
b100100000100010000000000000010 R
b1001 Q
b10 P
b0 O
b0 N
b0 M
b100010000000000000010 L
b10 K
0J
b1111 I
b101 H
b1111 G
b101 F
b10 /
b1001 .
1-
b101 ,
0+
0*
0)
b1111 (
1'
1&
b10 %
b1001 $
b0 #
1"
0!
$end
#10
0"
#20
b1 K
b1 -"
b1 1"
b11 V
b11 s
b11 ,"
b1 P
b1 n
b1 r
b1 +"
b1 W
b1 a
b1 q
b1 U
b1 ^
b1 o
b1 x
b100100000000000000001 L
b100100000000000000001 y
b1 S
b1 ]
b10010 X
b10010 0"
b1 %
b1 /
b1 T
b0 N
b0 p
b0 t
b0 2"
b100100000100100000000000000001 R
b100100000100100000000000000001 v
b11000000001000 \
b11000000001000 ("
b11000000001000 )"
b10001 4"
b11000000000100 [
b11000000000100 u
b11000000000100 z
b11000000000100 *"
1!
b1 #
#40
0!
b10 #
#60
1+
b100010000000000000001 L
b100010000000000000001 y
b10001 X
b10001 0"
b1000 $
b1000 .
b1000 Q
b10 N
b10 p
b10 t
b10 2"
b100000000100010000000000000001 R
b100000000100010000000000000001 v
b11000000001100 \
b11000000001100 ("
b11000000001100 )"
b10010 4"
b11000000001000 [
b11000000001000 u
b11000000001000 z
b11000000001000 *"
1!
b11 #
#80
0!
b100 #
#100
b10 K
b10 -"
b10 1"
b1 V
b1 s
b1 ,"
b10 P
b10 n
b10 r
b10 +"
b10 W
b10 a
b10 q
b10 U
b10 ^
b10 o
b10 x
b100100000000000000010 L
b100100000000000000010 y
b10 S
b10 ]
b10010 X
b10010 0"
b10 %
b10 /
b10 T
b1 N
b1 p
b1 t
b1 2"
b100000000100100000000000000010 R
b100000000100100000000000000010 v
b11000000010000 \
b11000000010000 ("
b11000000010000 )"
b10001 4"
b11000000001100 [
b11000000001100 u
b11000000001100 z
b11000000001100 *"
1!
b101 #
#120
0!
b110 #
#140
b11 K
b11 -"
b11 1"
b110 V
b110 s
b110 ,"
b11 P
b11 n
b11 r
b11 +"
b11111111111111111001100000100000 U
b11111111111111111001100000100000 ^
b11111111111111111001100000100000 o
b11111111111111111001100000100000 x
b1 O
b1 b
b1 3"
b10 ,
b10 F
b10 H
b10 _
0-
0'
b10001100101001100000100000 L
b10001100101001100000100000 y
b1001100000100000 S
b1001100000100000 ]
b10011 Z
b10011 ."
b10001 Y
b10001 /"
b100000 %
b100000 /
b100000 T
b0 $
b0 .
b0 Q
b10 N
b10 p
b10 t
b10 2"
b10001100101001100000100000 R
b10001100101001100000100000 v
b11000000010100 \
b11000000010100 ("
b11000000010100 )"
b10010 4"
b11000000010000 [
b11000000010000 u
b11000000010000 z
b11000000010000 *"
1!
b111 #
#160
0!
b1000 #
#180
b1 K
b1 -"
b1 1"
b1 W
b1 a
b1 q
0J
b11 V
b11 s
b11 ,"
b1 P
b1 n
b1 r
b1 +"
b11111111111111111001100000100010 U
b11111111111111111001100000100010 ^
b11111111111111111001100000100010 o
b11111111111111111001100000100010 x
b1 N
b1 p
b1 t
b1 2"
b10 O
b10 b
b10 3"
b110 ,
b110 F
b110 H
b110 _
b10010100011001100000100010 L
b10010100011001100000100010 y
b1001100000100010 S
b1001100000100010 ]
b10001 X
b10001 0"
b10010 Y
b10010 /"
b100010 %
b100010 /
b100010 T
b10010100011001100000100010 R
b10010100011001100000100010 v
b11000000011000 \
b11000000011000 ("
b11000000011000 )"
b10011 4"
b11000000010100 [
b11000000010100 u
b11000000010100 z
b11000000010100 *"
1!
b1001 #
#200
0!
b1010 #
#220
b11111111111111111001100000100100 U
b11111111111111111001100000100100 ^
b11111111111111111001100000100100 o
b11111111111111111001100000100100 x
b1 O
b1 b
b1 3"
b0 ,
b0 F
b0 H
b0 _
b10001100111001100000100100 L
b10001100111001100000100100 y
b1001100000100100 S
b1001100000100100 ]
b10011 X
b10011 0"
b10001 Y
b10001 /"
b100100 %
b100100 /
b100100 T
b10001100111001100000100100 R
b10001100111001100000100100 v
b11000000011100 \
b11000000011100 ("
b11000000011100 )"
b11000000011000 [
b11000000011000 u
b11000000011000 z
b11000000011000 *"
1!
b1011 #
#240
0!
b1100 #
#260
b11111111111111111001100000100101 U
b11111111111111111001100000100101 ^
b11111111111111111001100000100101 o
b11111111111111111001100000100101 x
b1 ,
b1 F
b1 H
b1 _
b10001100111001100000100101 L
b10001100111001100000100101 y
b1001100000100101 S
b1001100000100101 ]
b100101 %
b100101 /
b100101 T
b10001100111001100000100101 R
b10001100111001100000100101 v
b11000000100000 \
b11000000100000 ("
b11000000100000 )"
b11000000011100 [
b11000000011100 u
b11000000011100 z
b11000000011100 *"
1!
b1101 #
#280
0!
b1110 #
#300
b11 K
b11 -"
b11 1"
b110 V
b110 s
b110 ,"
b11 P
b11 n
b11 r
b11 +"
b10 W
b10 a
b10 q
b10 U
b10 ^
b10 o
b10 x
b100 ,
b100 F
b100 H
b100 _
1-
1'
b10001100110000000000000010 L
b10001100110000000000000010 y
b10 S
b10 ]
b0 Z
b0 ."
b10 %
b10 /
b10 T
b1101 $
b1101 .
b1101 Q
b110110001100110000000000000010 R
b110110001100110000000000000010 v
b11000000100100 \
b11000000100100 ("
b11000000100100 )"
b11000000100000 [
b11000000100000 u
b11000000100000 z
b11000000100000 *"
1!
b1111 #
#320
0!
b10000 #
#340
b10 K
b10 -"
b10 1"
b1 V
b1 s
b1 ,"
b10 P
b10 n
b10 r
b10 +"
b11 W
b11 a
b11 q
b11111111111111111001100000100110 U
b11111111111111111001100000100110 ^
b11111111111111111001100000100110 o
b11111111111111111001100000100110 x
b11 ,
b11 F
b11 H
b11 _
0-
0'
b10001100111001100000100110 L
b10001100111001100000100110 y
b1001100000100110 S
b1001100000100110 ]
b10011 Z
b10011 ."
b100110 %
b100110 /
b100110 T
b0 $
b0 .
b0 Q
b11 N
b11 p
b11 t
b11 2"
b10001100111001100000100110 R
b10001100111001100000100110 v
b11000000101000 \
b11000000101000 ("
b11000000101000 )"
b11000000100100 [
b11000000100100 u
b11000000100100 z
b11000000100100 *"
1!
b10001 #
#360
0!
b10010 #
#380
b10 U
b10 ^
b10 o
b10 x
b0 O
b0 b
b0 3"
b101 ,
b101 F
b101 H
b101 _
0+
1-
1'
b10 W
b10 a
b10 q
b100010000000000000010 L
b100010000000000000010 y
b10 S
b10 ]
b0 Z
b0 ."
b10001 X
b10001 0"
b0 Y
b0 /"
b10 %
b10 /
b10 T
b1001 $
b1001 .
b1001 Q
b1 N
b1 p
b1 t
b1 2"
b100100000100010000000000000010 R
b100100000100010000000000000010 v
b11000000101100 \
b11000000101100 ("
b11000000101100 )"
b11000000101000 [
b11000000101000 u
b11000000101000 z
b11000000101000 *"
1!
b10011 #
#400
0!
b10100 #
#420
b1 K
b1 -"
b1 1"
b11 V
b11 s
b11 ,"
b1 P
b1 n
b1 r
b1 +"
b1 W
b1 a
b1 q
b1 U
b1 ^
b1 o
b1 x
b100100000000000000001 L
b100100000000000000001 y
b1 S
b1 ]
b10010 X
b10010 0"
b1 %
b1 /
b1 T
b10 N
b10 p
b10 t
b10 2"
b100100000100100000000000000001 R
b100100000100100000000000000001 v
b11000000110000 \
b11000000110000 ("
b11000000110000 )"
b10001 4"
b11000000101100 [
b11000000101100 u
b11000000101100 z
b11000000101100 *"
1!
b10101 #
#440
0!
b10110 #
#460
b0 K
b0 -"
b0 1"
1J
b100 V
b100 s
b100 ,"
b0 P
b0 n
b0 r
b0 +"
b1001100000101010 U
b1001100000101010 ^
b1001100000101010 o
b1001100000101010 x
b10 O
b10 b
b10 3"
b111 ,
b111 F
b111 H
b111 _
0-
0'
b10001100101001100000101010 L
b10001100101001100000101010 y
b1001100000101010 S
b1001100000101010 ]
b10011 Z
b10011 ."
b10001 Y
b10001 /"
b101010 %
b101010 /
b101010 T
b0 $
b0 .
b0 Q
b1 N
b1 p
b1 t
b1 2"
b10001100101001100000101010 R
b10001100101001100000101010 v
b11000000110100 \
b11000000110100 ("
b11000000110100 )"
b10010 4"
b11000000110000 [
b11000000110000 u
b11000000110000 z
b11000000110000 *"
1!
b10111 #
#480
0!
b11000 #
